LICENSE
MANIFEST.in
README.md
pyproject.toml
setup.py
external/json/nlohmann/json.hpp
external/rl-tools/include/rl_tools/rl_tools.h
external/rl-tools/include/rl_tools/universe.h
external/rl-tools/include/rl_tools/version.h
external/rl-tools/include/rl_tools/containers/matrix/matrix.h
external/rl-tools/include/rl_tools/containers/matrix/operations_arm.h
external/rl-tools/include/rl_tools/containers/matrix/operations_cpu.h
external/rl-tools/include/rl_tools/containers/matrix/operations_cpu_accelerate.h
external/rl-tools/include/rl_tools/containers/matrix/operations_cpu_blas.h
external/rl-tools/include/rl_tools/containers/matrix/operations_cpu_mkl.h
external/rl-tools/include/rl_tools/containers/matrix/operations_cpu_openblas.h
external/rl-tools/include/rl_tools/containers/matrix/operations_cuda.h
external/rl-tools/include/rl_tools/containers/matrix/operations_dummy.h
external/rl-tools/include/rl_tools/containers/matrix/operations_esp32.h
external/rl-tools/include/rl_tools/containers/matrix/operations_generic.h
external/rl-tools/include/rl_tools/containers/matrix/operations_wasm32.h
external/rl-tools/include/rl_tools/containers/matrix/persist.h
external/rl-tools/include/rl_tools/containers/matrix/persist_code.h
external/rl-tools/include/rl_tools/containers/tensor/operations_arm.h
external/rl-tools/include/rl_tools/containers/tensor/operations_cpu.h
external/rl-tools/include/rl_tools/containers/tensor/operations_cpu_accelerate.h
external/rl-tools/include/rl_tools/containers/tensor/operations_cpu_blas.h
external/rl-tools/include/rl_tools/containers/tensor/operations_cpu_mkl.h
external/rl-tools/include/rl_tools/containers/tensor/operations_cpu_openblas.h
external/rl-tools/include/rl_tools/containers/tensor/operations_cuda.h
external/rl-tools/include/rl_tools/containers/tensor/operations_generic.h
external/rl-tools/include/rl_tools/containers/tensor/persist.h
external/rl-tools/include/rl_tools/containers/tensor/persist_code.h
l2f.egg-info/PKG-INFO
l2f.egg-info/SOURCES.txt
l2f.egg-info/dependency_links.txt
l2f.egg-info/requires.txt
l2f.egg-info/top_level.txt
