Metadata-Version: 2.4
Name: l2f
Version: 2.0.16
Summary: Python bindings for the L2F (Learning to Fly) Simulator
Author: Jonas Eschmann
Author-email: Jonas Eschmann <jonas.eschmann@gmail.com>
Project-URL: Homepage, https://github.com/rl-tools/l2f
Project-URL: Issues, https://github.com/rl-tools/l2f/issues
Classifier: Programming Language :: Python :: 3
Classifier: License :: OSI Approved :: MIT License
Classifier: Operating System :: OS Independent
Requires-Python: >=3.8
License-File: LICENSE
Provides-Extra: examples
Requires-Dist: ui-server; extra == "examples"
Requires-Dist: foundation-policy; extra == "examples"
Dynamic: author
Dynamic: license-file
